
    {
        "address1":"14701 Charlson Road",
        "city":"Eden Prairie",
        "state":"MN",
        "zip":"55347-5076",
        "country":"United States",
        "phone":"952 683 2800",
        "website":"https:\/\/www.chrobinson.com",
        "industry":"Integrated Freight & Logistics",
        "industryKey":"integrated-freight-logistics",
        "industryDisp":"Integrated Freight & Logistics",
        "sector":"Industrials",
        "sectorKey":"industrials",
        "sectorDisp":"Industrials",
        "longBusinessSummary":"C.H. Robinson Worldwide, Inc., together with its subsidiaries, provides freight transportation services, and related logistics and supply chain services in the United States and internationally. It operates through two segments: North American Surface Transportation and Global Forwarding. The company offers transportation and logistics services, such as truckload, less than truckload transportation brokerage services, which include the shipment of single or multiple pallets of freight; intermodal transportation that comprises the shipment service of freight in containers or trailers by a combination of truck and rail; and non-vessel operating common carrier and freight forwarding services, as well as organizes air shipments and provides door-to-door services. It also provides customs brokerage services; and other logistics services, such as fee-based managed, warehousing, small parcel, and other services. It has contractual relationships with approximately 45,000 transportation companies, including motor carriers, railroads, and ocean and air carriers. In addition, the company is involved in the buying, selling, and\/or marketing of fresh fruits, vegetables, and other value-added perishable items under the Robinson Fresh brand name. Further, the company offers transportation management services or managed TMS; and other surface transportation services. It provides its fresh produce to grocery retailers, restaurants, produce wholesalers, and foodservice distributors through a network of independent produce growers and suppliers. The company was founded in 1905 and is headquartered in Eden Prairie, Minnesota.",
        "fullTimeEmployees":15246,
        "companyOfficers":[
            {
                "maxAge":1,
                "name":"Mr. Michael Paul Zechmeister",
                "age":56,
                "title":"Chief Financial Officer",
                "yearBorn":1967,
                "fiscalYear":2022,
                "totalPay":1748549,
                "exercisedValue":0,
                "unexercisedValue":940518
            },
            {
                "maxAge":1,
                "name":"Mr. Arun D. Rajan",
                "age":53,
                "title":"Chief Operating Officer",
                "yearBorn":1970,
                "fiscalYear":2022,
                "totalPay":2216300,
                "exercisedValue":0,
                "unexercisedValue":0
            },
            {
                "maxAge":1,
                "name":"Mr. Michael J. Short",
                "age":53,
                "title":"President of Global Freight Forwarding",
                "yearBorn":1970,
                "fiscalYear":2022,
                "totalPay":1476112,
                "exercisedValue":1022769,
                "unexercisedValue":155512
            },
            {
                "maxAge":1,
                "name":"Mr. David P. Bozeman",
                "age":55,
                "title":"President, CEO & Director",
                "yearBorn":1968,
                "fiscalYear":2022,
                "exercisedValue":0,
                "unexercisedValue":0
            },
            {
                "maxAge":1,
                "name":"Mr. Michael W. Neill",
                "age":52,
                "title":"Chief Technology Officer",
                "yearBorn":1971,
                "fiscalYear":2022,
                "exercisedValue":0,
                "unexercisedValue":0
            },
            {
                "maxAge":1,
                "name":"Mr. Charles S. Ives",
                "age":51,
                "title":"Director of Investor Relations",
                "yearBorn":1972,
                "fiscalYear":2022,
                "exercisedValue":0,
                "unexercisedValue":0
            },
            {
                "maxAge":1,
                "name":"Mr. Ben G. Campbell",
                "age":57,
                "title":"Chief Legal Officer & Secretary",
                "yearBorn":1966,
                "fiscalYear":2022,
                "exercisedValue":0,
                "unexercisedValue":0
            },
            {
                "maxAge":1,
                "name":"Mr. Duncan  Burns",
                "age":46,
                "title":"Chief Communications Officer",
                "yearBorn":1977,
                "fiscalYear":2022,
                "exercisedValue":0,
                "unexercisedValue":0
            },
            {
                "maxAge":1,
                "name":"Ms. Angela K. Freeman",
                "age":55,
                "title":"Chief Human Resources & ESG Officer",
                "yearBorn":1968,
                "fiscalYear":2022,
                "exercisedValue":0,
                "unexercisedValue":0
            },
            {
                "maxAge":1,
                "name":"Mr. Jordan T. Kass",
                "age":50,
                "title":"President of Managed Services",
                "yearBorn":1973,
                "fiscalYear":2022,
                "exercisedValue":0,
                "unexercisedValue":0
            }
        ],
        "auditRisk":1,
        "boardRisk":5,
        "compensationRisk":6,
        "shareHolderRightsRisk":8,
        "overallRisk":5,
        "governanceEpochDate":1709251200,
        "compensationAsOfEpochDate":1672444800,
        "maxAge":86400,
        "priceHint":2,
        "previousClose":73.95,
        "open":73.82,
        "dayLow":72.76,
        "dayHigh":74.43,
        "regularMarketPreviousClose":73.95,
        "regularMarketOpen":73.82,
        "regularMarketDayLow":72.76,
        "regularMarketDayHigh":74.43,
        "dividendRate":2.44,
        "dividendYield":0.033,
        "exDividendDate":1709164800,
        "payoutRatio":0.8971,
        "fiveYearAvgDividendYield":2.37,
        "beta":0.725,
        "trailingPE":27.334558,
        "forwardPE":18.495024,
        "volume":1351606,
        "regularMarketVolume":1351606,
        "averageVolume":1625455,
        "averageVolume10days":2502950,
        "averageDailyVolume10Day":2502950,
        "bid":74.34,
        "ask":74.41,
        "bidSize":300,
        "askSize":300,
        "marketCap":8690845696,
        "fiftyTwoWeekLow":69.11,
        "fiftyTwoWeekHigh":106.14,
        "priceToSalesTrailing12Months":0.49389789,
        "fiftyDayAverage":77.674,
        "twoHundredDayAverage":86.215,
        "currency":"USD",
        "enterpriseValue":10451048448,
        "profitMargins":0.018480001,
        "floatShares":116549439,
        "sharesOutstanding":116891000,
        "sharesShort":7651845,
        "sharesShortPriorMonth":8022252,
        "sharesShortPreviousMonthDate":1706659200,
        "dateShortInterest":1709164800,
        "sharesPercentSharesOut":0.0655,
        "heldPercentInsiders":0.00981,
        "heldPercentInstitutions":0.96362996,
        "shortRatio":4.29,
        "shortPercentOfFloat":0.0889,
        "impliedSharesOutstanding":116891000,
        "bookValue":12.15,
        "priceToBook":6.119342,
        "lastFiscalYearEnd":1703980800,
        "nextFiscalYearEnd":1735603200,
        "mostRecentQuarter":1703980800,
        "earningsQuarterlyGrowth":-0.678,
        "netIncomeToCommon":325128992,
        "trailingEps":2.72,
        "forwardEps":4.02,
        "pegRatio":-17.19,
        "lastSplitFactor":"2:1",
        "lastSplitDate":1129507200,
        "enterpriseToRevenue":0.594,
        "enterpriseToEbitda":17.646,
        "52WeekChange":-0.22051227,
        "SandP52WeekChange":0.32311738,
        "lastDividendValue":0.61,
        "lastDividendDate":1709164800,
        "exchange":"NMS",
        "quoteType":"EQUITY",
        "symbol":"CHRW",
        "underlyingSymbol":"CHRW",
        "shortName":"C.H. Robinson Worldwide, Inc.",
        "longName":"C.H. Robinson Worldwide, Inc.",
        "firstTradeDateEpochUtc":877008600,
        "timeZoneFullName":"America\/New_York",
        "timeZoneShortName":"EDT",
        "uuid":"b52e1320-f384-3b8d-9e63-4b201df63310",
        "messageBoardId":"finmb_368470",
        "gmtOffSetMilliseconds":-14400000,
        "currentPrice":74.35,
        "targetHighPrice":104.0,
        "targetLowPrice":60.0,
        "targetMeanPrice":80.84,
        "targetMedianPrice":80.0,
        "recommendationMean":3.2,
        "recommendationKey":"hold",
        "numberOfAnalystOpinions":19,
        "totalCash":145524000,
        "totalCashPerShare":1.245,
        "ebitda":592265024,
        "totalDebt":1952500992,
        "quickRatio":1.324,
        "currentRatio":1.404,
        "totalRevenue":17596442624,
        "debtToEquity":137.626,
        "revenuePerShare":148.429,
        "returnOnAssets":0.05949,
        "returnOnEquity":0.23457001,
        "freeCashflow":607872896,
        "operatingCashflow":731945984,
        "earningsGrowth":-0.679,
        "revenueGrowth":-0.167,
        "grossMargins":0.06564,
        "ebitdaMargins":0.03366,
        "operatingMargins":0.025390001,
        "financialCurrency":"USD",
        "trailingPegRatio":1.621
    }

